var lopcodes_8h =
[
    [ "checkopm", "lopcodes_8h.html#aa8c8723567bea374193abbc0fecd82cf", null ],
    [ "CREATE_ABCk", "lopcodes_8h.html#a9cb59013204285f8d899c8f3d88d2707", null ],
    [ "CREATE_ABx", "lopcodes_8h.html#a46bb00b89420c78407eb45a3bc98b50d", null ],
    [ "CREATE_Ax", "lopcodes_8h.html#ae08e838d4e7f9c8ed9b23a6a52d1b819", null ],
    [ "CREATE_sJ", "lopcodes_8h.html#a38d90774993bc1ec075f5705889f9982", null ],
    [ "GET_OPCODE", "lopcodes_8h.html#aaa146179c3677b790c5681dcd82f0acc", null ],
    [ "getarg", "lopcodes_8h.html#a34176ea971e0563a800c45073da2d09a", null ],
    [ "GETARG_A", "lopcodes_8h.html#a1d504abc1e2246548f89977210dce0b9", null ],
    [ "GETARG_Ax", "lopcodes_8h.html#acfd578bba038b6682b924cf48012d80a", null ],
    [ "GETARG_B", "lopcodes_8h.html#a7a343159ef7669a438c2097b839b2b13", null ],
    [ "GETARG_Bx", "lopcodes_8h.html#acf8d228275fd2789dcf5f019bbabc019", null ],
    [ "GETARG_C", "lopcodes_8h.html#af96cb84f2685fda7f36d3d099dba6a44", null ],
    [ "GETARG_k", "lopcodes_8h.html#aa9ce1e6169ccc23a1e9c783f61af343f", null ],
    [ "GETARG_sB", "lopcodes_8h.html#a7af64834446acb4afeec51438217c73d", null ],
    [ "GETARG_sBx", "lopcodes_8h.html#a1f61a823709ac7847e481290a596c480", null ],
    [ "GETARG_sC", "lopcodes_8h.html#a2dadd55729fda230ce1765caef7ea416", null ],
    [ "GETARG_sJ", "lopcodes_8h.html#a1e69b8e862462ab13df4acd8de7ef54c", null ],
    [ "getOpMode", "lopcodes_8h.html#afb3fdd221fb95fdd1c254f7ab479739e", null ],
    [ "int2sC", "lopcodes_8h.html#a1918af9b0bd50d9a0e6b3a4e243bbaad", null ],
    [ "isIT", "lopcodes_8h.html#ad8d4fbc03d23ff580e821c7fb6f07e3a", null ],
    [ "isOT", "lopcodes_8h.html#a9b8f96d6711b2f4fa021c770c9edffdb", null ],
    [ "L_INTHASBITS", "lopcodes_8h.html#aaefe4466d31a7397a337ee6f83bdc14f", null ],
    [ "LFIELDS_PER_FLUSH", "lopcodes_8h.html#a0888e2bcb54f6e603f09208763aadfe9", null ],
    [ "MASK0", "lopcodes_8h.html#ac38be540eada841367170e3764e93748", null ],
    [ "MASK1", "lopcodes_8h.html#aedd5e7a7ce381d9be03d198dce7db53f", null ],
    [ "MAXARG_A", "lopcodes_8h.html#ab3c4feecc8cd0add12e881e26bbb3b15", null ],
    [ "MAXARG_Ax", "lopcodes_8h.html#a742a1bed832225c3800b3f73eb8b20ec", null ],
    [ "MAXARG_B", "lopcodes_8h.html#ae5132046fa2196de46214613a36235b2", null ],
    [ "MAXARG_Bx", "lopcodes_8h.html#aebbf650de6e9cbec539bfabcb9ae50c6", null ],
    [ "MAXARG_C", "lopcodes_8h.html#a15a7daf14e4640990519e4e7f627900f", null ],
    [ "MAXARG_sJ", "lopcodes_8h.html#a25010bef992b79abb26404ddde6b47ee", null ],
    [ "MAXINDEXRK", "lopcodes_8h.html#a37cd6e85943ea87c9b99ef1ea6bcdb3e", null ],
    [ "NO_REG", "lopcodes_8h.html#a6552ce4b3bba3b1a820dc0adaf85974a", null ],
    [ "NUM_OPCODES", "lopcodes_8h.html#a1fb469ba81540d3314cfbe37c675ba20", null ],
    [ "OFFSET_sBx", "lopcodes_8h.html#afda4d6a4b816b12ffd722e04b20f0884", null ],
    [ "OFFSET_sC", "lopcodes_8h.html#aa857ab7e20a7c4cb44ec3b6d3d2ec2bd", null ],
    [ "OFFSET_sJ", "lopcodes_8h.html#a1618fbbbf634a1b231240cfd6f3a3e5f", null ],
    [ "opmode", "lopcodes_8h.html#a55f7a6110b36e7c0958f22fa82cd3c45", null ],
    [ "POS_A", "lopcodes_8h.html#a9a088c55af7f419a19a3228fd5048ef7", null ],
    [ "POS_Ax", "lopcodes_8h.html#a1df1ba0f129f8e4691da2c5e6d1ecc39", null ],
    [ "POS_B", "lopcodes_8h.html#ac71a05d32f83f3f83b05fa95bad8c953", null ],
    [ "POS_Bx", "lopcodes_8h.html#a3626b235301aa4d50a1eddfb650ddd87", null ],
    [ "POS_C", "lopcodes_8h.html#ab67ab8adf1f91e2c7e2b30b5345d214d", null ],
    [ "POS_k", "lopcodes_8h.html#af191be3002964d0ce1e4f56135fa42bc", null ],
    [ "POS_OP", "lopcodes_8h.html#a86559e8fac93f9aa28733fc4dd96af51", null ],
    [ "POS_sJ", "lopcodes_8h.html#a2e16ff1e3bdd4a468f0872517ebadc0a", null ],
    [ "sC2int", "lopcodes_8h.html#a68747af4969db9dc341d6dbff87e9c7a", null ],
    [ "SET_OPCODE", "lopcodes_8h.html#a9ae2b84a40beacf053969ff426aae06f", null ],
    [ "setarg", "lopcodes_8h.html#afb6645a4d916d7dab36ba5f6f658bb8a", null ],
    [ "SETARG_A", "lopcodes_8h.html#a01900876b9281238c6dbb4d7bc59ca66", null ],
    [ "SETARG_Ax", "lopcodes_8h.html#afeb0c89bdd47db50d0ba6b78bc894681", null ],
    [ "SETARG_B", "lopcodes_8h.html#a52ddcdcbd367c4557cc83c38e3e1723f", null ],
    [ "SETARG_Bx", "lopcodes_8h.html#a0c476ba8d647ec398f25bb6374a0c088", null ],
    [ "SETARG_C", "lopcodes_8h.html#a085f9af93bc2386ddb0b9fb53d5ff0b8", null ],
    [ "SETARG_k", "lopcodes_8h.html#ac3ce38dc1556d678ef023b240c97fde8", null ],
    [ "SETARG_sBx", "lopcodes_8h.html#ad28b4bc013c6ddae165ac998ebe321c7", null ],
    [ "SETARG_sJ", "lopcodes_8h.html#abfb44d9f7226140f97beb16afad6f6c3", null ],
    [ "SIZE_A", "lopcodes_8h.html#a205e8f662c5b2496cb7d9e7aa37cda90", null ],
    [ "SIZE_Ax", "lopcodes_8h.html#a52d077faf8699f2d66aef36bf4e6c751", null ],
    [ "SIZE_B", "lopcodes_8h.html#ac8795820709810bf0baf1660341cacc2", null ],
    [ "SIZE_Bx", "lopcodes_8h.html#a4b81cf762841df8820b6077b66c0c619", null ],
    [ "SIZE_C", "lopcodes_8h.html#a5f42703bf77b09689626ca8cf3fc5fc1", null ],
    [ "SIZE_OP", "lopcodes_8h.html#a4c1d995d13200130d713c6dc5e223c13", null ],
    [ "SIZE_sJ", "lopcodes_8h.html#a0746f1da0d525504790943f2b79b2856", null ],
    [ "testAMode", "lopcodes_8h.html#aaae51a1c7e304923c51509b7cd644f29", null ],
    [ "TESTARG_k", "lopcodes_8h.html#aa874f9aac8107c30bf683067661a988a", null ],
    [ "testITMode", "lopcodes_8h.html#ac5afff4b1215ce8a72b400c40834241b", null ],
    [ "testMMMode", "lopcodes_8h.html#a128c04f70b43fb82ed2eadb2b255cc81", null ],
    [ "testOTMode", "lopcodes_8h.html#a0d5c4bc6c8c7a22a6591c65a93d9c908", null ],
    [ "testTMode", "lopcodes_8h.html#a6750851f9d04ae7f9612146b07f88c97", null ],
    [ "OpCode", "lopcodes_8h.html#abeb7dfb0e9e2b3114e240a405d046ea7", [
      [ "OP_MOVE", "lopcodes_8h.html#abeb7dfb0e9e2b3114e240a405d046ea7addf83bbc02b6a88d325135c880d12184", null ],
      [ "OP_LOADI", "lopcodes_8h.html#abeb7dfb0e9e2b3114e240a405d046ea7a60de4d2d9c05216369b32f22325ac26c", null ],
      [ "OP_LOADF", "lopcodes_8h.html#abeb7dfb0e9e2b3114e240a405d046ea7a82da04477198d0562981ddd7d3adda8b", null ],
      [ "OP_LOADK", "lopcodes_8h.html#abeb7dfb0e9e2b3114e240a405d046ea7ab34a8eaf6d32d3c41810653d9eb99c1a", null ],
      [ "OP_LOADKX", "lopcodes_8h.html#abeb7dfb0e9e2b3114e240a405d046ea7ae95580de7b3877b66fdf87366b8e5887", null ],
      [ "OP_LOADFALSE", "lopcodes_8h.html#abeb7dfb0e9e2b3114e240a405d046ea7a8653663e33ebaa8572c7e76c86c6539d", null ],
      [ "OP_LFALSESKIP", "lopcodes_8h.html#abeb7dfb0e9e2b3114e240a405d046ea7a1163876c1d6575f1f220aca5be6751b8", null ],
      [ "OP_LOADTRUE", "lopcodes_8h.html#abeb7dfb0e9e2b3114e240a405d046ea7ac1fc81b1c2650990762cf656ac42540d", null ],
      [ "OP_LOADNIL", "lopcodes_8h.html#abeb7dfb0e9e2b3114e240a405d046ea7a5c399a98a26c923cdae3971b5e5b6432", null ],
      [ "OP_GETUPVAL", "lopcodes_8h.html#abeb7dfb0e9e2b3114e240a405d046ea7ab48573533495922f053a7d1c9b0d00b4", null ],
      [ "OP_SETUPVAL", "lopcodes_8h.html#abeb7dfb0e9e2b3114e240a405d046ea7a47df60373847890b47b447c870aea678", null ],
      [ "OP_GETTABUP", "lopcodes_8h.html#abeb7dfb0e9e2b3114e240a405d046ea7acba90301f3ac979a3edd23f74182367b", null ],
      [ "OP_GETTABLE", "lopcodes_8h.html#abeb7dfb0e9e2b3114e240a405d046ea7ab1ec2a36c59db7612249cc31e382fdd9", null ],
      [ "OP_GETI", "lopcodes_8h.html#abeb7dfb0e9e2b3114e240a405d046ea7a965a4251f6730e9c8e5ca9e4ba4d8568", null ],
      [ "OP_GETFIELD", "lopcodes_8h.html#abeb7dfb0e9e2b3114e240a405d046ea7ab8cb85274c0cd7f8d8525953bd844207", null ],
      [ "OP_SETTABUP", "lopcodes_8h.html#abeb7dfb0e9e2b3114e240a405d046ea7ac486cd83792b58a638e37cb249d54a7e", null ],
      [ "OP_SETTABLE", "lopcodes_8h.html#abeb7dfb0e9e2b3114e240a405d046ea7a34315d7408f31b006bf41c9e9c2d736e", null ],
      [ "OP_SETI", "lopcodes_8h.html#abeb7dfb0e9e2b3114e240a405d046ea7a51eb594f07db275f5c6a77621b2de777", null ],
      [ "OP_SETFIELD", "lopcodes_8h.html#abeb7dfb0e9e2b3114e240a405d046ea7a342ca5ec1477419948043acb24ef3032", null ],
      [ "OP_NEWTABLE", "lopcodes_8h.html#abeb7dfb0e9e2b3114e240a405d046ea7af4ae9eb9a3c88596112a1d99d0c66280", null ],
      [ "OP_SELF", "lopcodes_8h.html#abeb7dfb0e9e2b3114e240a405d046ea7a64bea18253f9e73c4c5fcfa6b0d5abd2", null ],
      [ "OP_ADDI", "lopcodes_8h.html#abeb7dfb0e9e2b3114e240a405d046ea7ae59b0459d271ccd33e3b5e525d8d82ec", null ],
      [ "OP_ADDK", "lopcodes_8h.html#abeb7dfb0e9e2b3114e240a405d046ea7aabeaee235c2d819809ba4179c9ad7c40", null ],
      [ "OP_SUBK", "lopcodes_8h.html#abeb7dfb0e9e2b3114e240a405d046ea7affb0b7800883712a266b8f74d7ed67de", null ],
      [ "OP_MULK", "lopcodes_8h.html#abeb7dfb0e9e2b3114e240a405d046ea7a2bb6b0300af606f3f17cc492e8a0fd9c", null ],
      [ "OP_MODK", "lopcodes_8h.html#abeb7dfb0e9e2b3114e240a405d046ea7acdf979ebf1cab75f05b47c659568a2c2", null ],
      [ "OP_POWK", "lopcodes_8h.html#abeb7dfb0e9e2b3114e240a405d046ea7a20894c12c21a091fc6b3965894a66a29", null ],
      [ "OP_DIVK", "lopcodes_8h.html#abeb7dfb0e9e2b3114e240a405d046ea7a8ea5e5bf7705ac9d64a421520f641561", null ],
      [ "OP_IDIVK", "lopcodes_8h.html#abeb7dfb0e9e2b3114e240a405d046ea7a9cf8f2bf4a89a2965fba615eb70da736", null ],
      [ "OP_BANDK", "lopcodes_8h.html#abeb7dfb0e9e2b3114e240a405d046ea7a257504b0bf681f2fbcb9395a3c4e7deb", null ],
      [ "OP_BORK", "lopcodes_8h.html#abeb7dfb0e9e2b3114e240a405d046ea7a57ac522387add616066acffc523b74f6", null ],
      [ "OP_BXORK", "lopcodes_8h.html#abeb7dfb0e9e2b3114e240a405d046ea7af49936a7a3eb6346a7f200981837265c", null ],
      [ "OP_SHRI", "lopcodes_8h.html#abeb7dfb0e9e2b3114e240a405d046ea7a9159011638ef566ddb323918488443e8", null ],
      [ "OP_SHLI", "lopcodes_8h.html#abeb7dfb0e9e2b3114e240a405d046ea7ab0da05be7645df562d8968b4f254df2b", null ],
      [ "OP_ADD", "lopcodes_8h.html#abeb7dfb0e9e2b3114e240a405d046ea7a96186829480e5b34b1373288e956b1c8", null ],
      [ "OP_SUB", "lopcodes_8h.html#abeb7dfb0e9e2b3114e240a405d046ea7a6c224b456bd394d4d8bad0631ca8e2b7", null ],
      [ "OP_MUL", "lopcodes_8h.html#abeb7dfb0e9e2b3114e240a405d046ea7aa0e08a6f94350f03d29e4a55d543ba2f", null ],
      [ "OP_MOD", "lopcodes_8h.html#abeb7dfb0e9e2b3114e240a405d046ea7a39c596fc7eae450b7218bd97126e37c9", null ],
      [ "OP_POW", "lopcodes_8h.html#abeb7dfb0e9e2b3114e240a405d046ea7a35127684be890cfd81d556dc84d5f9db", null ],
      [ "OP_DIV", "lopcodes_8h.html#abeb7dfb0e9e2b3114e240a405d046ea7a719aeab2140dd5f575d1559b95bf74e1", null ],
      [ "OP_IDIV", "lopcodes_8h.html#abeb7dfb0e9e2b3114e240a405d046ea7ac813f8b860222d35f2d02410a84f53b3", null ],
      [ "OP_BAND", "lopcodes_8h.html#abeb7dfb0e9e2b3114e240a405d046ea7a6410f6c403b6cd759180c8b8be874cac", null ],
      [ "OP_BOR", "lopcodes_8h.html#abeb7dfb0e9e2b3114e240a405d046ea7a2f4bd7bbcff0799872d56d31e258599b", null ],
      [ "OP_BXOR", "lopcodes_8h.html#abeb7dfb0e9e2b3114e240a405d046ea7afd5cb32a2593241c564d2cdce914021b", null ],
      [ "OP_SHL", "lopcodes_8h.html#abeb7dfb0e9e2b3114e240a405d046ea7a845012132d1f5f2d1cd125326476c25b", null ],
      [ "OP_SHR", "lopcodes_8h.html#abeb7dfb0e9e2b3114e240a405d046ea7a789f5e2846cb039c0273aff134011fd4", null ],
      [ "OP_MMBIN", "lopcodes_8h.html#abeb7dfb0e9e2b3114e240a405d046ea7a25acd5dff5083adb067889345ae100d6", null ],
      [ "OP_MMBINI", "lopcodes_8h.html#abeb7dfb0e9e2b3114e240a405d046ea7a2068a8603e2904d2abd826877ab9e516", null ],
      [ "OP_MMBINK", "lopcodes_8h.html#abeb7dfb0e9e2b3114e240a405d046ea7a023d51bef94e0b9450cce3b76788a229", null ],
      [ "OP_UNM", "lopcodes_8h.html#abeb7dfb0e9e2b3114e240a405d046ea7ae3fd0932f8be8e5e810d731fd60ab8ef", null ],
      [ "OP_BNOT", "lopcodes_8h.html#abeb7dfb0e9e2b3114e240a405d046ea7ada36dd48f6870a79b5998262341c57d6", null ],
      [ "OP_NOT", "lopcodes_8h.html#abeb7dfb0e9e2b3114e240a405d046ea7a36a6b73cc4823f54891a013e2cc760d1", null ],
      [ "OP_LEN", "lopcodes_8h.html#abeb7dfb0e9e2b3114e240a405d046ea7a55406931f4958f887e6d966d154a1931", null ],
      [ "OP_CONCAT", "lopcodes_8h.html#abeb7dfb0e9e2b3114e240a405d046ea7a28a7da14b1413b441cf2a5d433b43a51", null ],
      [ "OP_CLOSE", "lopcodes_8h.html#abeb7dfb0e9e2b3114e240a405d046ea7a9e771dc35104ec1246adba881d27e372", null ],
      [ "OP_TBC", "lopcodes_8h.html#abeb7dfb0e9e2b3114e240a405d046ea7a45ba48df2b6802b55eb5eef6bc66b749", null ],
      [ "OP_JMP", "lopcodes_8h.html#abeb7dfb0e9e2b3114e240a405d046ea7afd679fab86e6a91d22c91734e287639b", null ],
      [ "OP_EQ", "lopcodes_8h.html#abeb7dfb0e9e2b3114e240a405d046ea7a1634898deb6e4d1bcb15416034c641c5", null ],
      [ "OP_LT", "lopcodes_8h.html#abeb7dfb0e9e2b3114e240a405d046ea7a7d5ed006824d331041dad8486e52df50", null ],
      [ "OP_LE", "lopcodes_8h.html#abeb7dfb0e9e2b3114e240a405d046ea7acef6e71b662db063ff532d89500bb0c0", null ],
      [ "OP_EQK", "lopcodes_8h.html#abeb7dfb0e9e2b3114e240a405d046ea7ac474caab30c580d7a336de092e3e8754", null ],
      [ "OP_EQI", "lopcodes_8h.html#abeb7dfb0e9e2b3114e240a405d046ea7a073492f9f138556d12ee1020f01afa9d", null ],
      [ "OP_LTI", "lopcodes_8h.html#abeb7dfb0e9e2b3114e240a405d046ea7a7355d162e8b15877fe33c54e3b755746", null ],
      [ "OP_LEI", "lopcodes_8h.html#abeb7dfb0e9e2b3114e240a405d046ea7aec7e53f36f35ef810ecff8a7eb274877", null ],
      [ "OP_GTI", "lopcodes_8h.html#abeb7dfb0e9e2b3114e240a405d046ea7a4c9ef8190def252dc1e0deb1bf7e787e", null ],
      [ "OP_GEI", "lopcodes_8h.html#abeb7dfb0e9e2b3114e240a405d046ea7ade0bd78cc2f7ec9c1bf6c161759221fa", null ],
      [ "OP_TEST", "lopcodes_8h.html#abeb7dfb0e9e2b3114e240a405d046ea7a8952e66300f2660060e38c67ccd21c9d", null ],
      [ "OP_TESTSET", "lopcodes_8h.html#abeb7dfb0e9e2b3114e240a405d046ea7a39b4077a15fb8fffc166f5045dddacee", null ],
      [ "OP_CALL", "lopcodes_8h.html#abeb7dfb0e9e2b3114e240a405d046ea7a098bbeea13096667b102f7fd90cbe38f", null ],
      [ "OP_TAILCALL", "lopcodes_8h.html#abeb7dfb0e9e2b3114e240a405d046ea7aff2c07ebfd82aa22cc247e9855a16069", null ],
      [ "OP_RETURN", "lopcodes_8h.html#abeb7dfb0e9e2b3114e240a405d046ea7ad436c18b194473f5ec64c28b774e41b3", null ],
      [ "OP_RETURN0", "lopcodes_8h.html#abeb7dfb0e9e2b3114e240a405d046ea7ae3f8033d220b543563720de9ab788e82", null ],
      [ "OP_RETURN1", "lopcodes_8h.html#abeb7dfb0e9e2b3114e240a405d046ea7a85801949afc11b7d95553fd0ee912f38", null ],
      [ "OP_FORLOOP", "lopcodes_8h.html#abeb7dfb0e9e2b3114e240a405d046ea7aa01470a2fc70a3f2dbd20c7c8f270802", null ],
      [ "OP_FORPREP", "lopcodes_8h.html#abeb7dfb0e9e2b3114e240a405d046ea7a5277c6eb2b1ab790c4942fdccd749e33", null ],
      [ "OP_TFORPREP", "lopcodes_8h.html#abeb7dfb0e9e2b3114e240a405d046ea7aafeb9e3e631d6f6c1700bf77134d425e", null ],
      [ "OP_TFORCALL", "lopcodes_8h.html#abeb7dfb0e9e2b3114e240a405d046ea7a899602d2c96443e08eec9e477071aa22", null ],
      [ "OP_TFORLOOP", "lopcodes_8h.html#abeb7dfb0e9e2b3114e240a405d046ea7a7dabccd7671c8ff374cb4502a6edb9c0", null ],
      [ "OP_SETLIST", "lopcodes_8h.html#abeb7dfb0e9e2b3114e240a405d046ea7a01618d8295953fd4ab2ef721b2051718", null ],
      [ "OP_CLOSURE", "lopcodes_8h.html#abeb7dfb0e9e2b3114e240a405d046ea7a407a76cd8c503b0f4dc14603687a77a2", null ],
      [ "OP_VARARG", "lopcodes_8h.html#abeb7dfb0e9e2b3114e240a405d046ea7a1856103c50818d72aaa506821a4ef004", null ],
      [ "OP_VARARGPREP", "lopcodes_8h.html#abeb7dfb0e9e2b3114e240a405d046ea7a0ac7fd650d101088cfc6beed3757ba44", null ],
      [ "OP_EXTRAARG", "lopcodes_8h.html#abeb7dfb0e9e2b3114e240a405d046ea7ae7a29a9b5e1490453da04cba95b39bea", null ]
    ] ],
    [ "OpMode", "lopcodes_8h.html#a56752d1aeb4bd4940e632396072d68af", [
      [ "iABC", "lopcodes_8h.html#a56752d1aeb4bd4940e632396072d68afa5032b5bab05a3312f6236ad8a6053cf3", null ],
      [ "iABx", "lopcodes_8h.html#a56752d1aeb4bd4940e632396072d68afae162f330f7a1e7581cdbbb4af60dc8ea", null ],
      [ "iAsBx", "lopcodes_8h.html#a56752d1aeb4bd4940e632396072d68afa5db94456d16691b254a6b2fc7b473e55", null ],
      [ "iAx", "lopcodes_8h.html#a56752d1aeb4bd4940e632396072d68afa453db051897b5faf2716653c2aa5a2e2", null ],
      [ "isJ", "lopcodes_8h.html#a56752d1aeb4bd4940e632396072d68afa8c4168189c62aed69b9160daeb20f20e", null ]
    ] ]
];